<?xml version="1.0" encoding="UTF-8"?>
<CMapData>
 <name />
 <parent />
 <flags value="0" />
 <contentFlags value="1" />
 <streamingExtentsMin x="-1923.423" y="651.8807" z="-46.22536" />
 <streamingExtentsMax x="-1377.259" y="1198.743" z="380.7742" />
 <entitiesExtentsMin x="-1655.99" y="919.3137" z="153.7746" />
 <entitiesExtentsMax x="-1644.692" y="931.3105" z="180.7742" />
 <entities>
  <Item type="CEntityDef">
   <archetypeName>vbmototaxi</archetypeName>
   <flags value="32" />
   <guid value="0" />
   <position x="-1650.341" y="925.3122" z="175.0925" />
   <rotation x="0" y="0" z="0.2249508" w="0.9743702" />
   <scaleXY value="1" />
   <scaleZ value="1" />
   <parentIndex value="-1" />
   <lodDist value="120" />
   <childLodDist value="0" />
   <lodLevel>LODTYPES_DEPTH_ORPHANHD</lodLevel>
   <numChildren value="0" />
   <priorityLevel>PRI_REQUIRED</priorityLevel>
   <extensions />
   <ambientOcclusionMultiplier value="255" />
   <artificialAmbientOcclusion value="255" />
   <tintValue value="0" />
  </Item>
  <Item type="CEntityDef">
   <archetypeName>hash_2ACF481A</archetypeName>
   <flags value="2147483680" />
   <guid value="0" />
   <position x="-1649.013" y="920.3995" z="176.5121" />
   <rotation x="0" y="0" z="0.7253746" w="0.6883544" />
   <scaleXY value="1" />
   <scaleZ value="1" />
   <parentIndex value="-1" />
   <lodDist value="50" />
   <childLodDist value="0" />
   <lodLevel>LODTYPES_DEPTH_ORPHANHD</lodLevel>
   <numChildren value="0" />
   <priorityLevel>PRI_REQUIRED</priorityLevel>
   <extensions />
   <ambientOcclusionMultiplier value="255" />
   <artificialAmbientOcclusion value="255" />
   <tintValue value="0" />
  </Item>
  <Item type="CEntityDef">
   <archetypeName>hash_D3C2F298</archetypeName>
   <flags value="2147483680" />
   <guid value="0" />
   <position x="-1653.819" y="926.1929" z="176.6214" />
   <rotation x="0" y="0" z="-0.52992" w="0.8480477" />
   <scaleXY value="1" />
   <scaleZ value="1" />
   <parentIndex value="-1" />
   <lodDist value="50" />
   <childLodDist value="0" />
   <lodLevel>LODTYPES_DEPTH_ORPHANHD</lodLevel>
   <numChildren value="0" />
   <priorityLevel>PRI_REQUIRED</priorityLevel>
   <extensions />
   <ambientOcclusionMultiplier value="255" />
   <artificialAmbientOcclusion value="255" />
   <tintValue value="0" />
  </Item>
  <Item type="CEntityDef">
   <archetypeName>qsbalcao2</archetypeName>
   <flags value="2147483680" />
   <guid value="0" />
   <position x="-1652.394" y="928.8726" z="177.1342" />
   <rotation x="0" y="0" z="-0.52992" w="0.8480477" />
   <scaleXY value="1" />
   <scaleZ value="1" />
   <parentIndex value="-1" />
   <lodDist value="50" />
   <childLodDist value="0" />
   <lodLevel>LODTYPES_DEPTH_ORPHANHD</lodLevel>
   <numChildren value="0" />
   <priorityLevel>PRI_REQUIRED</priorityLevel>
   <extensions />
   <ambientOcclusionMultiplier value="255" />
   <artificialAmbientOcclusion value="255" />
   <tintValue value="0" />
  </Item>
  <Item type="CEntityDef">
   <archetypeName>hash_6309FDF9</archetypeName>
   <flags value="2147483680" />
   <guid value="0" />
   <position x="-1648.499" y="924.8119" z="176.6386" />
   <rotation x="0" y="0" z="-0.52992" w="0.8480477" />
   <scaleXY value="1" />
   <scaleZ value="1" />
   <parentIndex value="-1" />
   <lodDist value="50" />
   <childLodDist value="0" />
   <lodLevel>LODTYPES_DEPTH_ORPHANHD</lodLevel>
   <numChildren value="0" />
   <priorityLevel>PRI_REQUIRED</priorityLevel>
   <extensions />
   <ambientOcclusionMultiplier value="255" />
   <artificialAmbientOcclusion value="255" />
   <tintValue value="0" />
  </Item>
  <Item type="CEntityDef">
   <archetypeName>hash_7D81F60B</archetypeName>
   <flags value="2147483680" />
   <guid value="0" />
   <position x="-1652.468" y="929.4763" z="178.0007" />
   <rotation x="0" y="0" z="-0.52992" w="0.8480477" />
   <scaleXY value="1" />
   <scaleZ value="1" />
   <parentIndex value="-1" />
   <lodDist value="50" />
   <childLodDist value="0" />
   <lodLevel>LODTYPES_DEPTH_ORPHANHD</lodLevel>
   <numChildren value="0" />
   <priorityLevel>PRI_REQUIRED</priorityLevel>
   <extensions />
   <ambientOcclusionMultiplier value="255" />
   <artificialAmbientOcclusion value="255" />
   <tintValue value="0" />
  </Item>
  <Item type="CEntityDef">
   <archetypeName>hash_64015B84</archetypeName>
   <flags value="2147483680" />
   <guid value="0" />
   <position x="-1653.067" y="927.4606" z="176.6207" />
   <rotation x="0" y="0" z="-0.52992" w="0.8480477" />
   <scaleXY value="1" />
   <scaleZ value="1" />
   <parentIndex value="-1" />
   <lodDist value="50" />
   <childLodDist value="0" />
   <lodLevel>LODTYPES_DEPTH_ORPHANHD</lodLevel>
   <numChildren value="0" />
   <priorityLevel>PRI_REQUIRED</priorityLevel>
   <extensions />
   <ambientOcclusionMultiplier value="255" />
   <artificialAmbientOcclusion value="255" />
   <tintValue value="0" />
  </Item>
  <Item type="CEntityDef">
   <archetypeName>hash_E500CCC5</archetypeName>
   <flags value="2147483680" />
   <guid value="0" />
   <position x="-1651.506" y="930.5672" z="176.6134" />
   <rotation x="0" y="0" z="0.2249508" w="0.9743702" />
   <scaleXY value="1" />
   <scaleZ value="1" />
   <parentIndex value="-1" />
   <lodDist value="50" />
   <childLodDist value="0" />
   <lodLevel>LODTYPES_DEPTH_ORPHANHD</lodLevel>
   <numChildren value="0" />
   <priorityLevel>PRI_REQUIRED</priorityLevel>
   <extensions />
   <ambientOcclusionMultiplier value="255" />
   <artificialAmbientOcclusion value="255" />
   <tintValue value="0" />
  </Item>
  <Item type="CEntityDef">
   <archetypeName>hash_76E9F095</archetypeName>
   <flags value="2147483680" />
   <guid value="0" />
   <position x="-1650.429" y="930.0418" z="176.6195" />
   <rotation x="0" y="0" z="0.2249508" w="0.9743702" />
   <scaleXY value="1" />
   <scaleZ value="1" />
   <parentIndex value="-1" />
   <lodDist value="50" />
   <childLodDist value="0" />
   <lodLevel>LODTYPES_DEPTH_ORPHANHD</lodLevel>
   <numChildren value="0" />
   <priorityLevel>PRI_REQUIRED</priorityLevel>
   <extensions />
   <ambientOcclusionMultiplier value="255" />
   <artificialAmbientOcclusion value="255" />
   <tintValue value="0" />
  </Item>
  <Item type="CEntityDef">
   <archetypeName>hash_146EABA0</archetypeName>
   <flags value="2147483680" />
   <guid value="0" />
   <position x="-1649.389" y="929.5356" z="176.6195" />
   <rotation x="0" y="0" z="0.2249508" w="0.9743702" />
   <scaleXY value="1" />
   <scaleZ value="1" />
   <parentIndex value="-1" />
   <lodDist value="50" />
   <childLodDist value="0" />
   <lodLevel>LODTYPES_DEPTH_ORPHANHD</lodLevel>
   <numChildren value="0" />
   <priorityLevel>PRI_REQUIRED</priorityLevel>
   <extensions />
   <ambientOcclusionMultiplier value="255" />
   <artificialAmbientOcclusion value="255" />
   <tintValue value="0" />
  </Item>
  <Item type="CEntityDef">
   <archetypeName>hash_F9F1D0AD</archetypeName>
   <flags value="2147483680" />
   <guid value="0" />
   <position x="-1648.578" y="929.1409" z="176.6195" />
   <rotation x="0" y="0" z="0.2249508" w="0.9743702" />
   <scaleXY value="1" />
   <scaleZ value="1" />
   <parentIndex value="-1" />
   <lodDist value="50" />
   <childLodDist value="0" />
   <lodLevel>LODTYPES_DEPTH_ORPHANHD</lodLevel>
   <numChildren value="0" />
   <priorityLevel>PRI_REQUIRED</priorityLevel>
   <extensions />
   <ambientOcclusionMultiplier value="255" />
   <artificialAmbientOcclusion value="255" />
   <tintValue value="0" />
  </Item>
  <Item type="CEntityDef">
   <archetypeName>hash_DC1F5D6A</archetypeName>
   <flags value="2147483680" />
   <guid value="0" />
   <position x="-1650.819" y="930.2332" z="177.4854" />
   <rotation x="0" y="0" z="0.2249508" w="0.9743702" />
   <scaleXY value="1" />
   <scaleZ value="1" />
   <parentIndex value="-1" />
   <lodDist value="50" />
   <childLodDist value="0" />
   <lodLevel>LODTYPES_DEPTH_ORPHANHD</lodLevel>
   <numChildren value="0" />
   <priorityLevel>PRI_REQUIRED</priorityLevel>
   <extensions />
   <ambientOcclusionMultiplier value="255" />
   <artificialAmbientOcclusion value="255" />
   <tintValue value="0" />
  </Item>
  <Item type="CEntityDef">
   <archetypeName>hash_DC1F5D6A</archetypeName>
   <flags value="2147483680" />
   <guid value="0" />
   <position x="-1650.438" y="930.0464" z="177.4854" />
   <rotation x="0" y="0" z="0.2249508" w="0.9743702" />
   <scaleXY value="1" />
   <scaleZ value="1" />
   <parentIndex value="-1" />
   <lodDist value="50" />
   <childLodDist value="0" />
   <lodLevel>LODTYPES_DEPTH_ORPHANHD</lodLevel>
   <numChildren value="0" />
   <priorityLevel>PRI_REQUIRED</priorityLevel>
   <extensions />
   <ambientOcclusionMultiplier value="255" />
   <artificialAmbientOcclusion value="255" />
   <tintValue value="2" />
  </Item>
  <Item type="CEntityDef">
   <archetypeName>hash_809225F9</archetypeName>
   <flags value="2147483680" />
   <guid value="0" />
   <position x="-1650.102" y="929.8836" z="177.5053" />
   <rotation x="0" y="0" z="0.2249508" w="0.9743702" />
   <scaleXY value="1" />
   <scaleZ value="1" />
   <parentIndex value="-1" />
   <lodDist value="50" />
   <childLodDist value="0" />
   <lodLevel>LODTYPES_DEPTH_ORPHANHD</lodLevel>
   <numChildren value="0" />
   <priorityLevel>PRI_REQUIRED</priorityLevel>
   <extensions />
   <ambientOcclusionMultiplier value="255" />
   <artificialAmbientOcclusion value="255" />
   <tintValue value="4" />
  </Item>
  <Item type="CEntityDef">
   <archetypeName>hash_1FF3CC2E</archetypeName>
   <flags value="2147483680" />
   <guid value="0" />
   <position x="-1647.175" y="924.1652" z="176.6386" />
   <rotation x="0" y="0" z="0.8480477" w="0.52992" />
   <scaleXY value="1" />
   <scaleZ value="1" />
   <parentIndex value="-1" />
   <lodDist value="50" />
   <childLodDist value="0" />
   <lodLevel>LODTYPES_DEPTH_ORPHANHD</lodLevel>
   <numChildren value="0" />
   <priorityLevel>PRI_REQUIRED</priorityLevel>
   <extensions />
   <ambientOcclusionMultiplier value="255" />
   <artificialAmbientOcclusion value="255" />
   <tintValue value="0" />
  </Item>
  <Item type="CEntityDef">
   <archetypeName>hash_3DD687F3</archetypeName>
   <flags value="2147483680" />
   <guid value="0" />
   <position x="-1649.068" y="925.839" z="176.7178" />
   <rotation x="0" y="0" z="-0.4539909" w="0.8910063" />
   <scaleXY value="1" />
   <scaleZ value="1" />
   <parentIndex value="-1" />
   <lodDist value="50" />
   <childLodDist value="0" />
   <lodLevel>LODTYPES_DEPTH_ORPHANHD</lodLevel>
   <numChildren value="0" />
   <priorityLevel>PRI_REQUIRED</priorityLevel>
   <extensions />
   <ambientOcclusionMultiplier value="255" />
   <artificialAmbientOcclusion value="255" />
   <tintValue value="0" />
  </Item>
  <Item type="CEntityDef">
   <archetypeName>hash_3DD687F3</archetypeName>
   <flags value="2147483680" />
   <guid value="0" />
   <position x="-1649.812" y="924.7375" z="176.7178" />
   <rotation x="0" y="0" z="-0.5664071" w="0.8241255" />
   <scaleXY value="1" />
   <scaleZ value="1" />
   <parentIndex value="-1" />
   <lodDist value="50" />
   <childLodDist value="0" />
   <lodLevel>LODTYPES_DEPTH_ORPHANHD</lodLevel>
   <numChildren value="0" />
   <priorityLevel>PRI_REQUIRED</priorityLevel>
   <extensions />
   <ambientOcclusionMultiplier value="255" />
   <artificialAmbientOcclusion value="255" />
   <tintValue value="0" />
  </Item>
  <Item type="CEntityDef">
   <archetypeName>hash_F9F1D0AD</archetypeName>
   <flags value="2147483680" />
   <guid value="0" />
   <position x="-1651.2" y="924.8833" z="176.6195" />
   <rotation x="0" y="0" z="0.2249508" w="0.9743702" />
   <scaleXY value="1" />
   <scaleZ value="1" />
   <parentIndex value="-1" />
   <lodDist value="50" />
   <childLodDist value="0" />
   <lodLevel>LODTYPES_DEPTH_ORPHANHD</lodLevel>
   <numChildren value="0" />
   <priorityLevel>PRI_REQUIRED</priorityLevel>
   <extensions />
   <ambientOcclusionMultiplier value="255" />
   <artificialAmbientOcclusion value="255" />
   <tintValue value="0" />
  </Item>
  <Item type="CEntityDef">
   <archetypeName>hash_88476B1F</archetypeName>
   <flags value="2147483680" />
   <guid value="0" />
   <position x="-1646.638" y="925.0452" z="176.4834" />
   <rotation x="0" y="0" z="0.8480477" w="0.52992" />
   <scaleXY value="1" />
   <scaleZ value="1" />
   <parentIndex value="-1" />
   <lodDist value="50" />
   <childLodDist value="0" />
   <lodLevel>LODTYPES_DEPTH_ORPHANHD</lodLevel>
   <numChildren value="0" />
   <priorityLevel>PRI_REQUIRED</priorityLevel>
   <extensions />
   <ambientOcclusionMultiplier value="255" />
   <artificialAmbientOcclusion value="255" />
   <tintValue value="0" />
  </Item>
  <Item type="CEntityDef">
   <archetypeName>hash_FC205949</archetypeName>
   <flags value="2147483680" />
   <guid value="0" />
   <position x="-1648.802" y="927.468" z="177.6883" />
   <rotation x="0" y="0" z="0.8480477" w="0.52992" />
   <scaleXY value="1" />
   <scaleZ value="1" />
   <parentIndex value="-1" />
   <lodDist value="50" />
   <childLodDist value="0" />
   <lodLevel>LODTYPES_DEPTH_ORPHANHD</lodLevel>
   <numChildren value="0" />
   <priorityLevel>PRI_REQUIRED</priorityLevel>
   <extensions />
   <ambientOcclusionMultiplier value="255" />
   <artificialAmbientOcclusion value="255" />
   <tintValue value="0" />
  </Item>
  <Item type="CEntityDef">
   <archetypeName>hash_3F49EF87</archetypeName>
   <flags value="2147483680" />
   <guid value="0" />
   <position x="-1648.175" y="926.4662" z="178.5208" />
   <rotation x="0" y="0" z="0.2249508" w="0.9743702" />
   <scaleXY value="1" />
   <scaleZ value="1" />
   <parentIndex value="-1" />
   <lodDist value="50" />
   <childLodDist value="0" />
   <lodLevel>LODTYPES_DEPTH_ORPHANHD</lodLevel>
   <numChildren value="0" />
   <priorityLevel>PRI_REQUIRED</priorityLevel>
   <extensions />
   <ambientOcclusionMultiplier value="255" />
   <artificialAmbientOcclusion value="255" />
   <tintValue value="0" />
  </Item>
  <Item type="CEntityDef">
   <archetypeName>hash_042DF94C</archetypeName>
   <flags value="2147483680" />
   <guid value="0" />
   <position x="-1647.151" y="925.9662" z="178.5208" />
   <rotation x="0" y="0" z="0.2249508" w="0.9743702" />
   <scaleXY value="1" />
   <scaleZ value="1" />
   <parentIndex value="-1" />
   <lodDist value="50" />
   <childLodDist value="0" />
   <lodLevel>LODTYPES_DEPTH_ORPHANHD</lodLevel>
   <numChildren value="0" />
   <priorityLevel>PRI_REQUIRED</priorityLevel>
   <extensions />
   <ambientOcclusionMultiplier value="255" />
   <artificialAmbientOcclusion value="255" />
   <tintValue value="0" />
  </Item>
  <Item type="CEntityDef">
   <archetypeName>hash_42F45560</archetypeName>
   <flags value="2147483680" />
   <guid value="0" />
   <position x="-1651.156" y="928.1991" z="177.7312" />
   <rotation x="0" y="0" z="-0.9969173" w="-0.07846038" />
   <scaleXY value="1" />
   <scaleZ value="1" />
   <parentIndex value="-1" />
   <lodDist value="50" />
   <childLodDist value="0" />
   <lodLevel>LODTYPES_DEPTH_ORPHANHD</lodLevel>
   <numChildren value="0" />
   <priorityLevel>PRI_REQUIRED</priorityLevel>
   <extensions />
   <ambientOcclusionMultiplier value="255" />
   <artificialAmbientOcclusion value="255" />
   <tintValue value="0" />
  </Item>
  <Item type="CEntityDef">
   <archetypeName>hash_C71F2E9C</archetypeName>
   <flags value="2147483680" />
   <guid value="0" />
   <position x="-1651.541" y="928.6085" z="177.6611" />
   <rotation x="0" y="0" z="-0.9743702" w="0.2249508" />
   <scaleXY value="1" />
   <scaleZ value="1" />
   <parentIndex value="-1" />
   <lodDist value="50" />
   <childLodDist value="0" />
   <lodLevel>LODTYPES_DEPTH_ORPHANHD</lodLevel>
   <numChildren value="0" />
   <priorityLevel>PRI_REQUIRED</priorityLevel>
   <extensions />
   <ambientOcclusionMultiplier value="255" />
   <artificialAmbientOcclusion value="255" />
   <tintValue value="0" />
  </Item>
  <Item type="CEntityDef">
   <archetypeName>hash_EEEFB5EC</archetypeName>
   <flags value="2147483680" />
   <guid value="0" />
   <position x="-1651.916" y="928.7052" z="177.6598" />
   <rotation x="0" y="0" z="-0.9743702" w="0.2249508" />
   <scaleXY value="1" />
   <scaleZ value="1" />
   <parentIndex value="-1" />
   <lodDist value="50" />
   <childLodDist value="0" />
   <lodLevel>LODTYPES_DEPTH_ORPHANHD</lodLevel>
   <numChildren value="0" />
   <priorityLevel>PRI_REQUIRED</priorityLevel>
   <extensions />
   <ambientOcclusionMultiplier value="255" />
   <artificialAmbientOcclusion value="255" />
   <tintValue value="0" />
  </Item>
  <Item type="CEntityDef">
   <archetypeName>hash_92F001A2</archetypeName>
   <flags value="2147483680" />
   <guid value="0" />
   <position x="-1651.539" y="929.1746" z="176.6301" />
   <rotation x="0" y="0" z="-0.9743702" w="0.2249508" />
   <scaleXY value="1" />
   <scaleZ value="1" />
   <parentIndex value="-1" />
   <lodDist value="50" />
   <childLodDist value="0" />
   <lodLevel>LODTYPES_DEPTH_ORPHANHD</lodLevel>
   <numChildren value="0" />
   <priorityLevel>PRI_REQUIRED</priorityLevel>
   <extensions />
   <ambientOcclusionMultiplier value="255" />
   <artificialAmbientOcclusion value="255" />
   <tintValue value="0" />
  </Item>
  <Item type="CEntityDef">
   <archetypeName>hash_8FD0E6B3</archetypeName>
   <flags value="2147483680" />
   <guid value="0" />
   <position x="-1650.695" y="925.9949" z="178.5432" />
   <rotation x="0" y="0" z="0.2249508" w="0.9743702" />
   <scaleXY value="1" />
   <scaleZ value="1" />
   <parentIndex value="-1" />
   <lodDist value="50" />
   <childLodDist value="0" />
   <lodLevel>LODTYPES_DEPTH_ORPHANHD</lodLevel>
   <numChildren value="0" />
   <priorityLevel>PRI_REQUIRED</priorityLevel>
   <extensions />
   <ambientOcclusionMultiplier value="255" />
   <artificialAmbientOcclusion value="255" />
   <tintValue value="0" />
  </Item>
  <Item type="CEntityDef">
   <archetypeName>hash_8FD0E6B3</archetypeName>
   <flags value="2147483680" />
   <guid value="0" />
   <position x="-1651.45" y="922.3066" z="178.3477" />
   <rotation x="0" y="0" z="0.2249508" w="0.9743702" />
   <scaleXY value="1" />
   <scaleZ value="1" />
   <parentIndex value="-1" />
   <lodDist value="50" />
   <childLodDist value="0" />
   <lodLevel>LODTYPES_DEPTH_ORPHANHD</lodLevel>
   <numChildren value="0" />
   <priorityLevel>PRI_REQUIRED</priorityLevel>
   <extensions />
   <ambientOcclusionMultiplier value="255" />
   <artificialAmbientOcclusion value="255" />
   <tintValue value="0" />
  </Item>
  <Item type="CEntityDef">
   <archetypeName>hash_F25FE3FD</archetypeName>
   <flags value="2147483680" />
   <guid value="0" />
   <position x="-1651.392" y="923.8694" z="176.6311" />
   <rotation x="0" y="0" z="0.2249508" w="0.9743702" />
   <scaleXY value="1" />
   <scaleZ value="1" />
   <parentIndex value="-1" />
   <lodDist value="50" />
   <childLodDist value="0" />
   <lodLevel>LODTYPES_DEPTH_ORPHANHD</lodLevel>
   <numChildren value="0" />
   <priorityLevel>PRI_REQUIRED</priorityLevel>
   <extensions />
   <ambientOcclusionMultiplier value="255" />
   <artificialAmbientOcclusion value="255" />
   <tintValue value="0" />
  </Item>
  <Item type="CEntityDef">
   <archetypeName>tijoloqs1</archetypeName>
   <flags value="2147483680" />
   <guid value="0" />
   <position x="-1655.117" y="923.5046" z="176.6311" />
   <rotation x="0" y="0" z="-0.9743702" w="0.2249508" />
   <scaleXY value="1" />
   <scaleZ value="1" />
   <parentIndex value="-1" />
   <lodDist value="50" />
   <childLodDist value="0" />
   <lodLevel>LODTYPES_DEPTH_ORPHANHD</lodLevel>
   <numChildren value="0" />
   <priorityLevel>PRI_REQUIRED</priorityLevel>
   <extensions />
   <ambientOcclusionMultiplier value="255" />
   <artificialAmbientOcclusion value="255" />
   <tintValue value="0" />
  </Item>
  <Item type="CEntityDef">
   <archetypeName>quebradashopgraf491</archetypeName>
   <flags value="2147483680" />
   <guid value="0" />
   <position x="-1649.528" y="923.3855" z="176.9072" />
   <rotation x="0" y="0" z="0.2249508" w="0.9743702" />
   <scaleXY value="1.055049" />
   <scaleZ value="0.9262975" />
   <parentIndex value="-1" />
   <lodDist value="50" />
   <childLodDist value="0" />
   <lodLevel>LODTYPES_DEPTH_ORPHANHD</lodLevel>
   <numChildren value="0" />
   <priorityLevel>PRI_REQUIRED</priorityLevel>
   <extensions />
   <ambientOcclusionMultiplier value="255" />
   <artificialAmbientOcclusion value="255" />
   <tintValue value="0" />
  </Item>
  <Item type="CEntityDef">
   <archetypeName>quebradashopgraf518</archetypeName>
   <flags value="2147483680" />
   <guid value="0" />
   <position x="-1652.122" y="921.0299" z="179.2634" />
   <rotation x="0" y="0" z="0.2249508" w="0.9743702" />
   <scaleXY value="1.712502" />
   <scaleZ value="0.5152297" />
   <parentIndex value="-1" />
   <lodDist value="50" />
   <childLodDist value="0" />
   <lodLevel>LODTYPES_DEPTH_ORPHANHD</lodLevel>
   <numChildren value="0" />
   <priorityLevel>PRI_REQUIRED</priorityLevel>
   <extensions />
   <ambientOcclusionMultiplier value="255" />
   <artificialAmbientOcclusion value="255" />
   <tintValue value="0" />
  </Item>
 </entities>
 <containerLods itemType="rage__fwContainerLodDef" />
 <boxOccluders itemType="BoxOccluder" />
 <occludeModels itemType="OccludeModel" />
 <physicsDictionaries />
 <instancedData>
  <ImapLink />
  <PropInstanceList itemType="rage__fwPropInstanceListDef" />
  <GrassInstanceList itemType="rage__fwGrassInstanceListDef" />
 </instancedData>
 <timeCycleModifiers itemType="CTimeCycleModifier" />
 <carGenerators itemType="CCarGen" />
 <LODLightsSOA>
  <direction itemType="FloatXYZ" />
  <falloff />
  <falloffExponent />
  <timeAndStateFlags />
  <hash />
  <coneInnerAngle />
  <coneOuterAngleOrCapExt />
  <coronaIntensity />
 </LODLightsSOA>
 <DistantLODLightsSOA>
  <position itemType="FloatXYZ" />
  <RGBI />
  <numStreetLights value="0" />
  <category value="0" />
 </DistantLODLightsSOA>
 <block>
  <version value="0" />
  <flags value="0" />
  <name></name>
  <exportedBy>CodeWalker</exportedBy>
  <owner></owner>
  <time>05 julho 2026 06:13</time>
 </block>
</CMapData>
