<?xml version="1.0" encoding="UTF-8"?>
<CMapData>
 <name />
 <parent />
 <flags value="0" />
 <contentFlags value="1" />
 <streamingExtentsMin x="2513.23" y="1723.532" z="-145.0814" />
 <streamingExtentsMax x="2997.034" y="2203.756" z="293.2363" />
 <entitiesExtentsMin x="2747.717" y="1958.019" z="54.91865" />
 <entitiesExtentsMax x="2762.547" y="1969.269" z="93.23635" />
 <entities>
  <Item type="CEntityDef">
   <archetypeName>hash_A6031949</archetypeName>
   <flags value="32" />
   <guid value="0" />
   <position x="2755.132" y="1963.644" z="84.68735" />
   <rotation x="0" y="0" z="-0.09584546" w="-0.9953963" />
   <scaleXY value="1" />
   <scaleZ value="1" />
   <parentIndex value="-1" />
   <lodDist value="120" />
   <childLodDist value="0" />
   <lodLevel>LODTYPES_DEPTH_ORPHANHD</lodLevel>
   <numChildren value="0" />
   <priorityLevel>PRI_REQUIRED</priorityLevel>
   <extensions />
   <ambientOcclusionMultiplier value="255" />
   <artificialAmbientOcclusion value="255" />
   <tintValue value="0" />
  </Item>
  <Item type="CEntityDef">
   <archetypeName>hash_CF5F1839</archetypeName>
   <flags value="1572865" />
   <guid value="0" />
   <position x="2755.272" y="1960.967" z="78.95471" />
   <rotation x="0" y="0" z="-0.09584546" w="-0.9953963" />
   <scaleXY value="1" />
   <scaleZ value="1" />
   <parentIndex value="-1" />
   <lodDist value="120" />
   <childLodDist value="0" />
   <lodLevel>LODTYPES_DEPTH_ORPHANHD</lodLevel>
   <numChildren value="0" />
   <priorityLevel>PRI_REQUIRED</priorityLevel>
   <extensions />
   <ambientOcclusionMultiplier value="255" />
   <artificialAmbientOcclusion value="255" />
   <tintValue value="0" />
  </Item>
  <Item type="CEntityDef">
   <archetypeName>hash_CF5F1839</archetypeName>
   <flags value="1572864" />
   <guid value="0" />
   <position x="2757.422" y="1967.346" z="88.30808" />
   <rotation x="0" y="0" z="-0.6360783" w="0.7716246" />
   <scaleXY value="1" />
   <scaleZ value="1" />
   <parentIndex value="-1" />
   <lodDist value="120" />
   <childLodDist value="0" />
   <lodLevel>LODTYPES_DEPTH_ORPHANHD</lodLevel>
   <numChildren value="0" />
   <priorityLevel>PRI_REQUIRED</priorityLevel>
   <extensions />
   <ambientOcclusionMultiplier value="255" />
   <artificialAmbientOcclusion value="255" />
   <tintValue value="0" />
  </Item>
  <Item type="CEntityDef">
   <archetypeName>hash_115D9EA5</archetypeName>
   <flags value="2147483680" />
   <guid value="0" />
   <position x="2761.214" y="1966.161" z="87.5559" />
   <rotation x="0" y="0" z="0.5075385" w="0.8616291" />
   <scaleXY value="1" />
   <scaleZ value="1" />
   <parentIndex value="-1" />
   <lodDist value="50" />
   <childLodDist value="0" />
   <lodLevel>LODTYPES_DEPTH_ORPHANHD</lodLevel>
   <numChildren value="0" />
   <priorityLevel>PRI_REQUIRED</priorityLevel>
   <extensions />
   <ambientOcclusionMultiplier value="255" />
   <artificialAmbientOcclusion value="255" />
   <tintValue value="0" />
  </Item>
  <Item type="CEntityDef">
   <archetypeName>hash_124608A4</archetypeName>
   <flags value="2147483680" />
   <guid value="0" />
   <position x="2761.191" y="1964.841" z="87.1334" />
   <rotation x="0" y="0" z="0.7716245" w="0.6360783" />
   <scaleXY value="1" />
   <scaleZ value="1" />
   <parentIndex value="-1" />
   <lodDist value="50" />
   <childLodDist value="0" />
   <lodLevel>LODTYPES_DEPTH_ORPHANHD</lodLevel>
   <numChildren value="0" />
   <priorityLevel>PRI_REQUIRED</priorityLevel>
   <extensions />
   <ambientOcclusionMultiplier value="255" />
   <artificialAmbientOcclusion value="255" />
   <tintValue value="0" />
  </Item>
  <Item type="CEntityDef">
   <archetypeName>hash_357EADDE</archetypeName>
   <flags value="2147483680" />
   <guid value="0" />
   <position x="2760.33" y="1965.168" z="87.1334" />
   <rotation x="0" y="0" z="-0.6360783" w="0.7716246" />
   <scaleXY value="1" />
   <scaleZ value="1" />
   <parentIndex value="-1" />
   <lodDist value="50" />
   <childLodDist value="0" />
   <lodLevel>LODTYPES_DEPTH_ORPHANHD</lodLevel>
   <numChildren value="0" />
   <priorityLevel>PRI_REQUIRED</priorityLevel>
   <extensions />
   <ambientOcclusionMultiplier value="255" />
   <artificialAmbientOcclusion value="255" />
   <tintValue value="0" />
  </Item>
  <Item type="CEntityDef">
   <archetypeName>hash_B56C3FB8</archetypeName>
   <flags value="2147483680" />
   <guid value="0" />
   <position x="2760.924" y="1963.536" z="87.60939" />
   <rotation x="0" y="0" z="0.7716245" w="0.6360783" />
   <scaleXY value="1" />
   <scaleZ value="1" />
   <parentIndex value="-1" />
   <lodDist value="50" />
   <childLodDist value="0" />
   <lodLevel>LODTYPES_DEPTH_ORPHANHD</lodLevel>
   <numChildren value="0" />
   <priorityLevel>PRI_REQUIRED</priorityLevel>
   <extensions />
   <ambientOcclusionMultiplier value="255" />
   <artificialAmbientOcclusion value="255" />
   <tintValue value="0" />
  </Item>
  <Item type="CEntityDef">
   <archetypeName>hash_62A8149F</archetypeName>
   <flags value="1572864" />
   <guid value="0" />
   <position x="2758.307" y="1964.531" z="88.30919" />
   <rotation x="0" y="0" z="-0.9953962" w="0.09584572" />
   <scaleXY value="1" />
   <scaleZ value="1" />
   <parentIndex value="-1" />
   <lodDist value="120" />
   <childLodDist value="0" />
   <lodLevel>LODTYPES_DEPTH_ORPHANHD</lodLevel>
   <numChildren value="0" />
   <priorityLevel>PRI_REQUIRED</priorityLevel>
   <extensions />
   <ambientOcclusionMultiplier value="255" />
   <artificialAmbientOcclusion value="255" />
   <tintValue value="0" />
  </Item>
  <Item type="CEntityDef">
   <archetypeName>hash_2D9F731B</archetypeName>
   <flags value="2147483680" />
   <guid value="0" />
   <position x="2760.143" y="1960.231" z="87.1402" />
   <rotation x="0" y="0" z="0.7716245" w="0.6360783" />
   <scaleXY value="1" />
   <scaleZ value="1" />
   <parentIndex value="-1" />
   <lodDist value="50" />
   <childLodDist value="0" />
   <lodLevel>LODTYPES_DEPTH_ORPHANHD</lodLevel>
   <numChildren value="0" />
   <priorityLevel>PRI_REQUIRED</priorityLevel>
   <extensions />
   <ambientOcclusionMultiplier value="255" />
   <artificialAmbientOcclusion value="255" />
   <tintValue value="0" />
  </Item>
  <Item type="CEntityDef">
   <archetypeName>hash_B6818EE0</archetypeName>
   <flags value="2147483680" />
   <guid value="0" />
   <position x="2760.555" y="1962.352" z="87.01411" />
   <rotation x="0" y="0" z="0.7716245" w="0.6360783" />
   <scaleXY value="1" />
   <scaleZ value="1" />
   <parentIndex value="-1" />
   <lodDist value="50" />
   <childLodDist value="0" />
   <lodLevel>LODTYPES_DEPTH_ORPHANHD</lodLevel>
   <numChildren value="0" />
   <priorityLevel>PRI_REQUIRED</priorityLevel>
   <extensions />
   <ambientOcclusionMultiplier value="255" />
   <artificialAmbientOcclusion value="255" />
   <tintValue value="0" />
  </Item>
  <Item type="CEntityDef">
   <archetypeName>hash_B6818EE0</archetypeName>
   <flags value="2147483680" />
   <guid value="0" />
   <position x="2760.555" y="1962.352" z="87.45438" />
   <rotation x="0" y="0" z="0.7716245" w="0.6360783" />
   <scaleXY value="1" />
   <scaleZ value="1" />
   <parentIndex value="-1" />
   <lodDist value="50" />
   <childLodDist value="0" />
   <lodLevel>LODTYPES_DEPTH_ORPHANHD</lodLevel>
   <numChildren value="0" />
   <priorityLevel>PRI_REQUIRED</priorityLevel>
   <extensions />
   <ambientOcclusionMultiplier value="255" />
   <artificialAmbientOcclusion value="255" />
   <tintValue value="0" />
  </Item>
  <Item type="CEntityDef">
   <archetypeName>hash_E7F10145</archetypeName>
   <flags value="2147483680" />
   <guid value="0" />
   <position x="2757.172" y="1960.753" z="87.15503" />
   <rotation x="0" y="0" z="0.9953963" w="-0.09584546" />
   <scaleXY value="1" />
   <scaleZ value="1" />
   <parentIndex value="-1" />
   <lodDist value="50" />
   <childLodDist value="0" />
   <lodLevel>LODTYPES_DEPTH_ORPHANHD</lodLevel>
   <numChildren value="0" />
   <priorityLevel>PRI_REQUIRED</priorityLevel>
   <extensions />
   <ambientOcclusionMultiplier value="255" />
   <artificialAmbientOcclusion value="255" />
   <tintValue value="0" />
  </Item>
  <Item type="CEntityDef">
   <archetypeName>hash_8868017D</archetypeName>
   <flags value="2147483680" />
   <guid value="0" />
   <position x="2757.583" y="1964.238" z="87.15503" />
   <rotation x="0" y="0" z="0.09584546" w="0.9953963" />
   <scaleXY value="1" />
   <scaleZ value="1" />
   <parentIndex value="-1" />
   <lodDist value="50" />
   <childLodDist value="0" />
   <lodLevel>LODTYPES_DEPTH_ORPHANHD</lodLevel>
   <numChildren value="0" />
   <priorityLevel>PRI_REQUIRED</priorityLevel>
   <extensions />
   <ambientOcclusionMultiplier value="255" />
   <artificialAmbientOcclusion value="255" />
   <tintValue value="0" />
  </Item>
  <Item type="CEntityDef">
   <archetypeName>hash_CC8478D8</archetypeName>
   <flags value="2147483680" />
   <guid value="0" />
   <position x="2756.974" y="1962.181" z="87.15503" />
   <rotation x="0" y="0" z="0.09584546" w="0.9953963" />
   <scaleXY value="1" />
   <scaleZ value="1" />
   <parentIndex value="-1" />
   <lodDist value="50" />
   <childLodDist value="0" />
   <lodLevel>LODTYPES_DEPTH_ORPHANHD</lodLevel>
   <numChildren value="0" />
   <priorityLevel>PRI_REQUIRED</priorityLevel>
   <extensions />
   <ambientOcclusionMultiplier value="255" />
   <artificialAmbientOcclusion value="255" />
   <tintValue value="0" />
  </Item>
  <Item type="CEntityDef">
   <archetypeName>hash_CC8478D8</archetypeName>
   <flags value="2147483680" />
   <guid value="0" />
   <position x="2757.106" y="1962.86" z="87.15503" />
   <rotation x="0" y="0" z="0.09584546" w="0.9953963" />
   <scaleXY value="1" />
   <scaleZ value="1" />
   <parentIndex value="-1" />
   <lodDist value="50" />
   <childLodDist value="0" />
   <lodLevel>LODTYPES_DEPTH_ORPHANHD</lodLevel>
   <numChildren value="0" />
   <priorityLevel>PRI_REQUIRED</priorityLevel>
   <extensions />
   <ambientOcclusionMultiplier value="255" />
   <artificialAmbientOcclusion value="255" />
   <tintValue value="0" />
  </Item>
  <Item type="CEntityDef">
   <archetypeName>hash_CC8478D8</archetypeName>
   <flags value="2147483680" />
   <guid value="0" />
   <position x="2757.035" y="1962.5" z="87.62535" />
   <rotation x="0" y="0" z="0.09584546" w="0.9953963" />
   <scaleXY value="1" />
   <scaleZ value="1" />
   <parentIndex value="-1" />
   <lodDist value="50" />
   <childLodDist value="0" />
   <lodLevel>LODTYPES_DEPTH_ORPHANHD</lodLevel>
   <numChildren value="0" />
   <priorityLevel>PRI_REQUIRED</priorityLevel>
   <extensions />
   <ambientOcclusionMultiplier value="255" />
   <artificialAmbientOcclusion value="255" />
   <tintValue value="0" />
  </Item>
  <Item type="CEntityDef">
   <archetypeName>hash_95F357DB</archetypeName>
   <flags value="2147483680" />
   <guid value="0" />
   <position x="2757.031" y="1962.524" z="88.43969" />
   <rotation x="0" y="0" z="-0.760406" w="0.6494479" />
   <scaleXY value="1" />
   <scaleZ value="1" />
   <parentIndex value="-1" />
   <lodDist value="50" />
   <childLodDist value="0" />
   <lodLevel>LODTYPES_DEPTH_ORPHANHD</lodLevel>
   <numChildren value="0" />
   <priorityLevel>PRI_REQUIRED</priorityLevel>
   <extensions />
   <ambientOcclusionMultiplier value="255" />
   <artificialAmbientOcclusion value="255" />
   <tintValue value="0" />
  </Item>
  <Item type="CEntityDef">
   <archetypeName>hash_CF5F1839</archetypeName>
   <flags value="1572864" />
   <guid value="0" />
   <position x="2753.452" y="1962.896" z="85.20551" />
   <rotation x="0" y="0" z="-0.6360783" w="0.7716246" />
   <scaleXY value="1" />
   <scaleZ value="1" />
   <parentIndex value="-1" />
   <lodDist value="120" />
   <childLodDist value="0" />
   <lodLevel>LODTYPES_DEPTH_ORPHANHD</lodLevel>
   <numChildren value="0" />
   <priorityLevel>PRI_REQUIRED</priorityLevel>
   <extensions />
   <ambientOcclusionMultiplier value="255" />
   <artificialAmbientOcclusion value="255" />
   <tintValue value="0" />
  </Item>
  <Item type="CEntityDef">
   <archetypeName>hash_F222C55F</archetypeName>
   <flags value="2147483680" />
   <guid value="0" />
   <position x="2752.405" y="1961.028" z="84.30628" />
   <rotation x="0" y="0" z="0.9953963" w="-0.09584546" />
   <scaleXY value="1" />
   <scaleZ value="1" />
   <parentIndex value="-1" />
   <lodDist value="50" />
   <childLodDist value="0" />
   <lodLevel>LODTYPES_DEPTH_ORPHANHD</lodLevel>
   <numChildren value="0" />
   <priorityLevel>PRI_REQUIRED</priorityLevel>
   <extensions />
   <ambientOcclusionMultiplier value="255" />
   <artificialAmbientOcclusion value="255" />
   <tintValue value="0" />
  </Item>
  <Item type="CEntityDef">
   <archetypeName>hash_F222C55F</archetypeName>
   <flags value="2147483680" />
   <guid value="0" />
   <position x="2751.354" y="1961.233" z="84.30628" />
   <rotation x="0" y="0" z="0.9953963" w="-0.09584546" />
   <scaleXY value="1" />
   <scaleZ value="1" />
   <parentIndex value="-1" />
   <lodDist value="50" />
   <childLodDist value="0" />
   <lodLevel>LODTYPES_DEPTH_ORPHANHD</lodLevel>
   <numChildren value="0" />
   <priorityLevel>PRI_REQUIRED</priorityLevel>
   <extensions />
   <ambientOcclusionMultiplier value="255" />
   <artificialAmbientOcclusion value="255" />
   <tintValue value="0" />
  </Item>
  <Item type="CEntityDef">
   <archetypeName>hash_F222C55F</archetypeName>
   <flags value="2147483680" />
   <guid value="0" />
   <position x="2751.917" y="1961.124" z="84.83639" />
   <rotation x="0" y="0" z="0.9953963" w="-0.09584546" />
   <scaleXY value="1" />
   <scaleZ value="1" />
   <parentIndex value="-1" />
   <lodDist value="50" />
   <childLodDist value="0" />
   <lodLevel>LODTYPES_DEPTH_ORPHANHD</lodLevel>
   <numChildren value="0" />
   <priorityLevel>PRI_REQUIRED</priorityLevel>
   <extensions />
   <ambientOcclusionMultiplier value="255" />
   <artificialAmbientOcclusion value="255" />
   <tintValue value="0" />
  </Item>
  <Item type="CEntityDef">
   <archetypeName>hash_301DDDFA</archetypeName>
   <flags value="2147483680" />
   <guid value="0" />
   <position x="2753.001" y="1963.766" z="84.03095" />
   <rotation x="0" y="0" z="0.5075384" w="0.8616292" />
   <scaleXY value="1" />
   <scaleZ value="1" />
   <parentIndex value="-1" />
   <lodDist value="50" />
   <childLodDist value="0" />
   <lodLevel>LODTYPES_DEPTH_ORPHANHD</lodLevel>
   <numChildren value="0" />
   <priorityLevel>PRI_REQUIRED</priorityLevel>
   <extensions />
   <ambientOcclusionMultiplier value="255" />
   <artificialAmbientOcclusion value="255" />
   <tintValue value="0" />
  </Item>
  <Item type="CEntityDef">
   <archetypeName>hash_69F24B9A</archetypeName>
   <flags value="2147483680" />
   <guid value="0" />
   <position x="2753.221" y="1965.225" z="86.69301" />
   <rotation x="0" y="0" z="0.9953963" w="-0.09584546" />
   <scaleXY value="1" />
   <scaleZ value="1" />
   <parentIndex value="-1" />
   <lodDist value="50" />
   <childLodDist value="0" />
   <lodLevel>LODTYPES_DEPTH_ORPHANHD</lodLevel>
   <numChildren value="0" />
   <priorityLevel>PRI_REQUIRED</priorityLevel>
   <extensions />
   <ambientOcclusionMultiplier value="255" />
   <artificialAmbientOcclusion value="255" />
   <tintValue value="0" />
  </Item>
  <Item type="CEntityDef">
   <archetypeName>hash_AB11CC80</archetypeName>
   <flags value="2147483680" />
   <guid value="0" />
   <position x="2753.394" y="1966.114" z="86.69301" />
   <rotation x="0" y="0" z="0.9953963" w="-0.09584546" />
   <scaleXY value="1" />
   <scaleZ value="1" />
   <parentIndex value="-1" />
   <lodDist value="50" />
   <childLodDist value="0" />
   <lodLevel>LODTYPES_DEPTH_ORPHANHD</lodLevel>
   <numChildren value="0" />
   <priorityLevel>PRI_REQUIRED</priorityLevel>
   <extensions />
   <ambientOcclusionMultiplier value="255" />
   <artificialAmbientOcclusion value="255" />
   <tintValue value="0" />
  </Item>
  <Item type="CEntityDef">
   <archetypeName>hash_69F24B9A</archetypeName>
   <flags value="2147483680" />
   <guid value="0" />
   <position x="2753.598" y="1967.163" z="86.69301" />
   <rotation x="0" y="0" z="0.9953963" w="-0.09584546" />
   <scaleXY value="1" />
   <scaleZ value="1" />
   <parentIndex value="-1" />
   <lodDist value="50" />
   <childLodDist value="0" />
   <lodLevel>LODTYPES_DEPTH_ORPHANHD</lodLevel>
   <numChildren value="0" />
   <priorityLevel>PRI_REQUIRED</priorityLevel>
   <extensions />
   <ambientOcclusionMultiplier value="255" />
   <artificialAmbientOcclusion value="255" />
   <tintValue value="0" />
  </Item>
  <Item type="CEntityDef">
   <archetypeName>hash_69F24B9A</archetypeName>
   <flags value="2147483680" />
   <guid value="0" />
   <position x="2750.593" y="1967.748" z="86.69301" />
   <rotation x="0" y="0" z="0.9953963" w="-0.09584546" />
   <scaleXY value="1" />
   <scaleZ value="1" />
   <parentIndex value="-1" />
   <lodDist value="50" />
   <childLodDist value="0" />
   <lodLevel>LODTYPES_DEPTH_ORPHANHD</lodLevel>
   <numChildren value="0" />
   <priorityLevel>PRI_REQUIRED</priorityLevel>
   <extensions />
   <ambientOcclusionMultiplier value="255" />
   <artificialAmbientOcclusion value="255" />
   <tintValue value="0" />
  </Item>
  <Item type="CEntityDef">
   <archetypeName>hash_AB11CC80</archetypeName>
   <flags value="2147483680" />
   <guid value="0" />
   <position x="2750.389" y="1966.698" z="86.69301" />
   <rotation x="0" y="0" z="0.9953963" w="-0.09584546" />
   <scaleXY value="1" />
   <scaleZ value="1" />
   <parentIndex value="-1" />
   <lodDist value="50" />
   <childLodDist value="0" />
   <lodLevel>LODTYPES_DEPTH_ORPHANHD</lodLevel>
   <numChildren value="0" />
   <priorityLevel>PRI_REQUIRED</priorityLevel>
   <extensions />
   <ambientOcclusionMultiplier value="255" />
   <artificialAmbientOcclusion value="255" />
   <tintValue value="0" />
  </Item>
  <Item type="CEntityDef">
   <archetypeName>hash_69F24B9A</archetypeName>
   <flags value="2147483680" />
   <guid value="0" />
   <position x="2750.216" y="1965.809" z="86.69301" />
   <rotation x="0" y="0" z="0.9953963" w="-0.09584546" />
   <scaleXY value="1" />
   <scaleZ value="1" />
   <parentIndex value="-1" />
   <lodDist value="50" />
   <childLodDist value="0" />
   <lodLevel>LODTYPES_DEPTH_ORPHANHD</lodLevel>
   <numChildren value="0" />
   <priorityLevel>PRI_REQUIRED</priorityLevel>
   <extensions />
   <ambientOcclusionMultiplier value="255" />
   <artificialAmbientOcclusion value="255" />
   <tintValue value="0" />
  </Item>
  <Item type="CEntityDef">
   <archetypeName>hash_1EEB7E4A</archetypeName>
   <flags value="2147483680" />
   <guid value="0" />
   <position x="2753.419" y="1966.156" z="84.0208" />
   <rotation x="0" y="0" z="0.6360784" w="-0.7716245" />
   <scaleXY value="1" />
   <scaleZ value="1" />
   <parentIndex value="-1" />
   <lodDist value="50" />
   <childLodDist value="0" />
   <lodLevel>LODTYPES_DEPTH_ORPHANHD</lodLevel>
   <numChildren value="0" />
   <priorityLevel>PRI_REQUIRED</priorityLevel>
   <extensions />
   <ambientOcclusionMultiplier value="255" />
   <artificialAmbientOcclusion value="255" />
   <tintValue value="0" />
  </Item>
  <Item type="CEntityDef">
   <archetypeName>hash_1EEB7E4A</archetypeName>
   <flags value="2147483680" />
   <guid value="0" />
   <position x="2750.331" y="1966.75" z="84.0208" />
   <rotation x="0" y="0" z="-0.7716245" w="-0.6360784" />
   <scaleXY value="1" />
   <scaleZ value="1" />
   <parentIndex value="-1" />
   <lodDist value="50" />
   <childLodDist value="0" />
   <lodLevel>LODTYPES_DEPTH_ORPHANHD</lodLevel>
   <numChildren value="0" />
   <priorityLevel>PRI_REQUIRED</priorityLevel>
   <extensions />
   <ambientOcclusionMultiplier value="255" />
   <artificialAmbientOcclusion value="255" />
   <tintValue value="0" />
  </Item>
  <Item type="CEntityDef">
   <archetypeName>hash_85F27D41</archetypeName>
   <flags value="2147483680" />
   <guid value="0" />
   <position x="2750.066" y="1965.39" z="84.04051" />
   <rotation x="0" y="0" z="-0.7716245" w="-0.6360784" />
   <scaleXY value="1" />
   <scaleZ value="1" />
   <parentIndex value="-1" />
   <lodDist value="50" />
   <childLodDist value="0" />
   <lodLevel>LODTYPES_DEPTH_ORPHANHD</lodLevel>
   <numChildren value="0" />
   <priorityLevel>PRI_REQUIRED</priorityLevel>
   <extensions />
   <ambientOcclusionMultiplier value="255" />
   <artificialAmbientOcclusion value="255" />
   <tintValue value="0" />
  </Item>
  <Item type="CEntityDef">
   <archetypeName>hash_85F27D41</archetypeName>
   <flags value="2147483680" />
   <guid value="0" />
   <position x="2750.637" y="1968.327" z="84.04051" />
   <rotation x="0" y="0" z="-0.7716245" w="-0.6360784" />
   <scaleXY value="1" />
   <scaleZ value="1" />
   <parentIndex value="-1" />
   <lodDist value="50" />
   <childLodDist value="0" />
   <lodLevel>LODTYPES_DEPTH_ORPHANHD</lodLevel>
   <numChildren value="0" />
   <priorityLevel>PRI_REQUIRED</priorityLevel>
   <extensions />
   <ambientOcclusionMultiplier value="255" />
   <artificialAmbientOcclusion value="255" />
   <tintValue value="0" />
  </Item>
  <Item type="CEntityDef">
   <archetypeName>hash_4932F486</archetypeName>
   <flags value="2147483680" />
   <guid value="0" />
   <position x="2749.838" y="1964.213" z="84.04051" />
   <rotation x="0" y="0" z="-0.7716245" w="-0.6360784" />
   <scaleXY value="1" />
   <scaleZ value="1" />
   <parentIndex value="-1" />
   <lodDist value="50" />
   <childLodDist value="0" />
   <lodLevel>LODTYPES_DEPTH_ORPHANHD</lodLevel>
   <numChildren value="0" />
   <priorityLevel>PRI_REQUIRED</priorityLevel>
   <extensions />
   <ambientOcclusionMultiplier value="255" />
   <artificialAmbientOcclusion value="255" />
   <tintValue value="0" />
  </Item>
  <Item type="CEntityDef">
   <archetypeName>hash_DF007C62</archetypeName>
   <flags value="2147483680" />
   <guid value="0" />
   <position x="2749.389" y="1961.905" z="84.04051" />
   <rotation x="0" y="0" z="-0.7716245" w="-0.6360784" />
   <scaleXY value="1" />
   <scaleZ value="1" />
   <parentIndex value="-1" />
   <lodDist value="50" />
   <childLodDist value="0" />
   <lodLevel>LODTYPES_DEPTH_ORPHANHD</lodLevel>
   <numChildren value="0" />
   <priorityLevel>PRI_REQUIRED</priorityLevel>
   <extensions />
   <ambientOcclusionMultiplier value="255" />
   <artificialAmbientOcclusion value="255" />
   <tintValue value="0" />
  </Item>
  <Item type="CEntityDef">
   <archetypeName>hash_DF007C62</archetypeName>
   <flags value="2147483680" />
   <guid value="0" />
   <position x="2749.616" y="1963.071" z="84.04051" />
   <rotation x="0" y="0" z="-0.7716245" w="-0.6360784" />
   <scaleXY value="1" />
   <scaleZ value="1" />
   <parentIndex value="-1" />
   <lodDist value="50" />
   <childLodDist value="0" />
   <lodLevel>LODTYPES_DEPTH_ORPHANHD</lodLevel>
   <numChildren value="0" />
   <priorityLevel>PRI_REQUIRED</priorityLevel>
   <extensions />
   <ambientOcclusionMultiplier value="255" />
   <artificialAmbientOcclusion value="255" />
   <tintValue value="0" />
  </Item>
  <Item type="CEntityDef">
   <archetypeName>hash_8FD0E6B3</archetypeName>
   <flags value="2147483680" />
   <guid value="0" />
   <position x="2751.832" y="1966.418" z="86.24649" />
   <rotation x="0" y="0" z="0.9953963" w="-0.09584546" />
   <scaleXY value="1" />
   <scaleZ value="1" />
   <parentIndex value="-1" />
   <lodDist value="50" />
   <childLodDist value="0" />
   <lodLevel>LODTYPES_DEPTH_ORPHANHD</lodLevel>
   <numChildren value="0" />
   <priorityLevel>PRI_REQUIRED</priorityLevel>
   <extensions />
   <ambientOcclusionMultiplier value="255" />
   <artificialAmbientOcclusion value="255" />
   <tintValue value="0" />
  </Item>
  <Item type="CEntityDef">
   <archetypeName>hash_8FD0E6B3</archetypeName>
   <flags value="2147483680" />
   <guid value="0" />
   <position x="2751.064" y="1962.471" z="86.24649" />
   <rotation x="0" y="0" z="0.9953963" w="-0.09584546" />
   <scaleXY value="1" />
   <scaleZ value="1" />
   <parentIndex value="-1" />
   <lodDist value="50" />
   <childLodDist value="0" />
   <lodLevel>LODTYPES_DEPTH_ORPHANHD</lodLevel>
   <numChildren value="0" />
   <priorityLevel>PRI_REQUIRED</priorityLevel>
   <extensions />
   <ambientOcclusionMultiplier value="255" />
   <artificialAmbientOcclusion value="255" />
   <tintValue value="0" />
  </Item>
  <Item type="CEntityDef">
   <archetypeName>hash_4D6410F7</archetypeName>
   <flags value="2147483680" />
   <guid value="0" />
   <position x="2753.661" y="1967.739" z="84.49723" />
   <rotation x="0" y="0" z="-0.7716245" w="-0.6360784" />
   <scaleXY value="1" />
   <scaleZ value="1" />
   <parentIndex value="-1" />
   <lodDist value="50" />
   <childLodDist value="0" />
   <lodLevel>LODTYPES_DEPTH_ORPHANHD</lodLevel>
   <numChildren value="0" />
   <priorityLevel>PRI_REQUIRED</priorityLevel>
   <extensions />
   <ambientOcclusionMultiplier value="255" />
   <artificialAmbientOcclusion value="255" />
   <tintValue value="0" />
  </Item>
  <Item type="CEntityDef">
   <archetypeName>hash_4D6410F7</archetypeName>
   <flags value="2147483680" />
   <guid value="0" />
   <position x="2753.073" y="1964.713" z="84.49723" />
   <rotation x="0" y="0" z="-0.7716245" w="-0.6360784" />
   <scaleXY value="1" />
   <scaleZ value="1" />
   <parentIndex value="-1" />
   <lodDist value="50" />
   <childLodDist value="0" />
   <lodLevel>LODTYPES_DEPTH_ORPHANHD</lodLevel>
   <numChildren value="0" />
   <priorityLevel>PRI_REQUIRED</priorityLevel>
   <extensions />
   <ambientOcclusionMultiplier value="255" />
   <artificialAmbientOcclusion value="255" />
   <tintValue value="0" />
  </Item>
  <Item type="CEntityDef">
   <archetypeName>hash_B39C85A4</archetypeName>
   <flags value="2147483680" />
   <guid value="0" />
   <position x="2751.068" y="1966.049" z="84.04614" />
   <rotation x="0" y="0" z="-0.8703555" w="-0.4924238" />
   <scaleXY value="1" />
   <scaleZ value="1" />
   <parentIndex value="-1" />
   <lodDist value="50" />
   <childLodDist value="0" />
   <lodLevel>LODTYPES_DEPTH_ORPHANHD</lodLevel>
   <numChildren value="0" />
   <priorityLevel>PRI_REQUIRED</priorityLevel>
   <extensions />
   <ambientOcclusionMultiplier value="255" />
   <artificialAmbientOcclusion value="255" />
   <tintValue value="0" />
  </Item>
  <Item type="CEntityDef">
   <archetypeName>hash_B39C85A4</archetypeName>
   <flags value="2147483680" />
   <guid value="0" />
   <position x="2752.502" y="1966.983" z="84.04614" />
   <rotation x="0" y="0" z="0.4924238" w="-0.8703556" />
   <scaleXY value="1" />
   <scaleZ value="1" />
   <parentIndex value="-1" />
   <lodDist value="50" />
   <childLodDist value="0" />
   <lodLevel>LODTYPES_DEPTH_ORPHANHD</lodLevel>
   <numChildren value="0" />
   <priorityLevel>PRI_REQUIRED</priorityLevel>
   <extensions />
   <ambientOcclusionMultiplier value="255" />
   <artificialAmbientOcclusion value="255" />
   <tintValue value="0" />
  </Item>
  <Item type="CEntityDef">
   <archetypeName>hash_CF5F1839</archetypeName>
   <flags value="1572864" />
   <guid value="0" />
   <position x="2757.422" y="1967.346" z="82.01113" />
   <rotation x="0" y="0" z="-0.6360783" w="0.7716246" />
   <scaleXY value="1" />
   <scaleZ value="1" />
   <parentIndex value="-1" />
   <lodDist value="120" />
   <childLodDist value="0" />
   <lodLevel>LODTYPES_DEPTH_ORPHANHD</lodLevel>
   <numChildren value="0" />
   <priorityLevel>PRI_REQUIRED</priorityLevel>
   <extensions />
   <ambientOcclusionMultiplier value="255" />
   <artificialAmbientOcclusion value="255" />
   <tintValue value="0" />
  </Item>
  <Item type="CEntityDef">
   <archetypeName>hash_62A8149F</archetypeName>
   <flags value="1572864" />
   <guid value="0" />
   <position x="2758.307" y="1964.531" z="82.01224" />
   <rotation x="0" y="0" z="-0.9953962" w="0.09584572" />
   <scaleXY value="1" />
   <scaleZ value="1" />
   <parentIndex value="-1" />
   <lodDist value="120" />
   <childLodDist value="0" />
   <lodLevel>LODTYPES_DEPTH_ORPHANHD</lodLevel>
   <numChildren value="0" />
   <priorityLevel>PRI_REQUIRED</priorityLevel>
   <extensions />
   <ambientOcclusionMultiplier value="255" />
   <artificialAmbientOcclusion value="255" />
   <tintValue value="0" />
  </Item>
  <Item type="CEntityDef">
   <archetypeName>hash_CFD218B9</archetypeName>
   <flags value="2147483680" />
   <guid value="0" />
   <position x="2760.99" y="1964.716" z="80.84604" />
   <rotation x="0" y="0" z="0.7716245" w="0.6360783" />
   <scaleXY value="1" />
   <scaleZ value="1" />
   <parentIndex value="-1" />
   <lodDist value="50" />
   <childLodDist value="0" />
   <lodLevel>LODTYPES_DEPTH_ORPHANHD</lodLevel>
   <numChildren value="0" />
   <priorityLevel>PRI_REQUIRED</priorityLevel>
   <extensions />
   <ambientOcclusionMultiplier value="255" />
   <artificialAmbientOcclusion value="255" />
   <tintValue value="0" />
  </Item>
  <Item type="CEntityDef">
   <archetypeName>hash_CFD218B9</archetypeName>
   <flags value="2147483680" />
   <guid value="0" />
   <position x="2761.235" y="1965.98" z="80.84604" />
   <rotation x="0" y="0" z="0.7716245" w="0.6360783" />
   <scaleXY value="1" />
   <scaleZ value="1" />
   <parentIndex value="-1" />
   <lodDist value="50" />
   <childLodDist value="0" />
   <lodLevel>LODTYPES_DEPTH_ORPHANHD</lodLevel>
   <numChildren value="0" />
   <priorityLevel>PRI_REQUIRED</priorityLevel>
   <extensions />
   <ambientOcclusionMultiplier value="255" />
   <artificialAmbientOcclusion value="255" />
   <tintValue value="0" />
  </Item>
  <Item type="CEntityDef">
   <archetypeName>hash_CFD218B9</archetypeName>
   <flags value="2147483680" />
   <guid value="0" />
   <position x="2761.105" y="1965.307" z="81.25163" />
   <rotation x="0" y="0" z="0.7716245" w="0.6360783" />
   <scaleXY value="1" />
   <scaleZ value="1" />
   <parentIndex value="-1" />
   <lodDist value="50" />
   <childLodDist value="0" />
   <lodLevel>LODTYPES_DEPTH_ORPHANHD</lodLevel>
   <numChildren value="0" />
   <priorityLevel>PRI_REQUIRED</priorityLevel>
   <extensions />
   <ambientOcclusionMultiplier value="255" />
   <artificialAmbientOcclusion value="255" />
   <tintValue value="0" />
  </Item>
  <Item type="CEntityDef">
   <archetypeName>hash_7E27D7D5</archetypeName>
   <flags value="2147483680" />
   <guid value="0" />
   <position x="2760.949" y="1963.471" z="80.85305" />
   <rotation x="0" y="0" z="0.7716245" w="0.6360783" />
   <scaleXY value="1" />
   <scaleZ value="1" />
   <parentIndex value="-1" />
   <lodDist value="50" />
   <childLodDist value="0" />
   <lodLevel>LODTYPES_DEPTH_ORPHANHD</lodLevel>
   <numChildren value="0" />
   <priorityLevel>PRI_REQUIRED</priorityLevel>
   <extensions />
   <ambientOcclusionMultiplier value="255" />
   <artificialAmbientOcclusion value="255" />
   <tintValue value="0" />
  </Item>
  <Item type="CEntityDef">
   <archetypeName>hash_4486B0AA</archetypeName>
   <flags value="2147483680" />
   <guid value="0" />
   <position x="2760.76" y="1962.501" z="80.85305" />
   <rotation x="0" y="0" z="0.7716245" w="0.6360783" />
   <scaleXY value="1" />
   <scaleZ value="1" />
   <parentIndex value="-1" />
   <lodDist value="50" />
   <childLodDist value="0" />
   <lodLevel>LODTYPES_DEPTH_ORPHANHD</lodLevel>
   <numChildren value="0" />
   <priorityLevel>PRI_REQUIRED</priorityLevel>
   <extensions />
   <ambientOcclusionMultiplier value="255" />
   <artificialAmbientOcclusion value="255" />
   <tintValue value="0" />
  </Item>
  <Item type="CEntityDef">
   <archetypeName>hash_B4ACA704</archetypeName>
   <flags value="2147483680" />
   <guid value="0" />
   <position x="2757.253" y="1964.064" z="81.32065" />
   <rotation x="0" y="0" z="0.7716245" w="0.6360783" />
   <scaleXY value="1" />
   <scaleZ value="1" />
   <parentIndex value="-1" />
   <lodDist value="50" />
   <childLodDist value="0" />
   <lodLevel>LODTYPES_DEPTH_ORPHANHD</lodLevel>
   <numChildren value="0" />
   <priorityLevel>PRI_REQUIRED</priorityLevel>
   <extensions />
   <ambientOcclusionMultiplier value="255" />
   <artificialAmbientOcclusion value="255" />
   <tintValue value="0" />
  </Item>
  <Item type="CEntityDef">
   <archetypeName>hash_E143B9B2</archetypeName>
   <flags value="2147483680" />
   <guid value="0" />
   <position x="2760.124" y="1960.61" z="80.82894" />
   <rotation x="0" y="0" z="0.7716245" w="0.6360783" />
   <scaleXY value="1" />
   <scaleZ value="1" />
   <parentIndex value="-1" />
   <lodDist value="50" />
   <childLodDist value="0" />
   <lodLevel>LODTYPES_DEPTH_ORPHANHD</lodLevel>
   <numChildren value="0" />
   <priorityLevel>PRI_REQUIRED</priorityLevel>
   <extensions />
   <ambientOcclusionMultiplier value="255" />
   <artificialAmbientOcclusion value="255" />
   <tintValue value="0" />
  </Item>
  <Item type="CEntityDef">
   <archetypeName>hash_E143B9B2</archetypeName>
   <flags value="2147483680" />
   <guid value="0" />
   <position x="2757.288" y="1960.294" z="80.82894" />
   <rotation x="0" y="0" z="0.09584546" w="0.9953963" />
   <scaleXY value="1" />
   <scaleZ value="1" />
   <parentIndex value="-1" />
   <lodDist value="50" />
   <childLodDist value="0" />
   <lodLevel>LODTYPES_DEPTH_ORPHANHD</lodLevel>
   <numChildren value="0" />
   <priorityLevel>PRI_REQUIRED</priorityLevel>
   <extensions />
   <ambientOcclusionMultiplier value="255" />
   <artificialAmbientOcclusion value="255" />
   <tintValue value="0" />
  </Item>
  <Item type="CEntityDef">
   <archetypeName>hash_B4ACA704</archetypeName>
   <flags value="2147483680" />
   <guid value="0" />
   <position x="2760.13" y="1963.744" z="81.32065" />
   <rotation x="0" y="0" z="-0.9953962" w="0.09584572" />
   <scaleXY value="1" />
   <scaleZ value="1" />
   <parentIndex value="-1" />
   <lodDist value="50" />
   <childLodDist value="0" />
   <lodLevel>LODTYPES_DEPTH_ORPHANHD</lodLevel>
   <numChildren value="0" />
   <priorityLevel>PRI_REQUIRED</priorityLevel>
   <extensions />
   <ambientOcclusionMultiplier value="255" />
   <artificialAmbientOcclusion value="255" />
   <tintValue value="0" />
  </Item>
  <Item type="CEntityDef">
   <archetypeName>hash_E5BD56D4</archetypeName>
   <flags value="2147483680" />
   <guid value="0" />
   <position x="2757.338" y="1962.336" z="80.75742" />
   <rotation x="0" y="0" z="0.7716245" w="0.6360783" />
   <scaleXY value="1" />
   <scaleZ value="1" />
   <parentIndex value="-1" />
   <lodDist value="50" />
   <childLodDist value="0" />
   <lodLevel>LODTYPES_DEPTH_ORPHANHD</lodLevel>
   <numChildren value="0" />
   <priorityLevel>PRI_REQUIRED</priorityLevel>
   <extensions />
   <ambientOcclusionMultiplier value="255" />
   <artificialAmbientOcclusion value="255" />
   <tintValue value="0" />
  </Item>
  <Item type="CEntityDef">
   <archetypeName>hash_60362CB4</archetypeName>
   <flags value="2147483680" />
   <guid value="0" />
   <position x="2757.288" y="1960.294" z="83.92838" />
   <rotation x="0" y="0" z="0.09584546" w="0.9953963" />
   <scaleXY value="1" />
   <scaleZ value="1" />
   <parentIndex value="-1" />
   <lodDist value="50" />
   <childLodDist value="0" />
   <lodLevel>LODTYPES_DEPTH_ORPHANHD</lodLevel>
   <numChildren value="0" />
   <priorityLevel>PRI_REQUIRED</priorityLevel>
   <extensions />
   <ambientOcclusionMultiplier value="255" />
   <artificialAmbientOcclusion value="255" />
   <tintValue value="0" />
  </Item>
  <Item type="CEntityDef">
   <archetypeName>hash_E846D990</archetypeName>
   <flags value="2147483680" />
   <guid value="0" />
   <position x="2756.872" y="1962.123" z="81.00314" />
   <rotation x="0" y="0" z="0.7716245" w="0.6360783" />
   <scaleXY value="1" />
   <scaleZ value="1" />
   <parentIndex value="-1" />
   <lodDist value="50" />
   <childLodDist value="0" />
   <lodLevel>LODTYPES_DEPTH_ORPHANHD</lodLevel>
   <numChildren value="0" />
   <priorityLevel>PRI_REQUIRED</priorityLevel>
   <extensions />
   <ambientOcclusionMultiplier value="255" />
   <artificialAmbientOcclusion value="255" />
   <tintValue value="0" />
  </Item>
  <Item type="CEntityDef">
   <archetypeName>hash_E846D990</archetypeName>
   <flags value="2147483680" />
   <guid value="0" />
   <position x="2757.413" y="1962.85" z="81.00314" />
   <rotation x="0" y="0" z="0.09584546" w="0.9953963" />
   <scaleXY value="1" />
   <scaleZ value="1" />
   <parentIndex value="-1" />
   <lodDist value="50" />
   <childLodDist value="0" />
   <lodLevel>LODTYPES_DEPTH_ORPHANHD</lodLevel>
   <numChildren value="0" />
   <priorityLevel>PRI_REQUIRED</priorityLevel>
   <extensions />
   <ambientOcclusionMultiplier value="255" />
   <artificialAmbientOcclusion value="255" />
   <tintValue value="0" />
  </Item>
  <Item type="CEntityDef">
   <archetypeName>hash_BF1B2B36</archetypeName>
   <flags value="2147483680" />
   <guid value="0" />
   <position x="2760.193" y="1964.601" z="81.28073" />
   <rotation x="0" y="0" z="0.7716245" w="0.6360783" />
   <scaleXY value="1" />
   <scaleZ value="1" />
   <parentIndex value="-1" />
   <lodDist value="50" />
   <childLodDist value="0" />
   <lodLevel>LODTYPES_DEPTH_ORPHANHD</lodLevel>
   <numChildren value="0" />
   <priorityLevel>PRI_REQUIRED</priorityLevel>
   <extensions />
   <ambientOcclusionMultiplier value="255" />
   <artificialAmbientOcclusion value="255" />
   <tintValue value="0" />
  </Item>
  <Item type="CEntityDef">
   <archetypeName>hash_8FD0E6B3</archetypeName>
   <flags value="2147483680" />
   <guid value="0" />
   <position x="2759.249" y="1965.795" z="83.05639" />
   <rotation x="0" y="0" z="0.9953963" w="-0.09584546" />
   <scaleXY value="1" />
   <scaleZ value="1" />
   <parentIndex value="-1" />
   <lodDist value="50" />
   <childLodDist value="0" />
   <lodLevel>LODTYPES_DEPTH_ORPHANHD</lodLevel>
   <numChildren value="0" />
   <priorityLevel>PRI_REQUIRED</priorityLevel>
   <extensions />
   <ambientOcclusionMultiplier value="255" />
   <artificialAmbientOcclusion value="255" />
   <tintValue value="0" />
  </Item>
  <Item type="CEntityDef">
   <archetypeName>hash_8FD0E6B3</archetypeName>
   <flags value="2147483680" />
   <guid value="0" />
   <position x="2758.597" y="1962.437" z="83.05639" />
   <rotation x="0" y="0" z="0.9953963" w="-0.09584546" />
   <scaleXY value="1" />
   <scaleZ value="1" />
   <parentIndex value="-1" />
   <lodDist value="50" />
   <childLodDist value="0" />
   <lodLevel>LODTYPES_DEPTH_ORPHANHD</lodLevel>
   <numChildren value="0" />
   <priorityLevel>PRI_REQUIRED</priorityLevel>
   <extensions />
   <ambientOcclusionMultiplier value="255" />
   <artificialAmbientOcclusion value="255" />
   <tintValue value="0" />
  </Item>
  <Item type="CEntityDef">
   <archetypeName>hash_62A8149F</archetypeName>
   <flags value="1572864" />
   <guid value="0" />
   <position x="2758.307" y="1964.531" z="78.84553" />
   <rotation x="0" y="0" z="-0.9953962" w="0.09584572" />
   <scaleXY value="1" />
   <scaleZ value="1" />
   <parentIndex value="-1" />
   <lodDist value="120" />
   <childLodDist value="0" />
   <lodLevel>LODTYPES_DEPTH_ORPHANHD</lodLevel>
   <numChildren value="0" />
   <priorityLevel>PRI_REQUIRED</priorityLevel>
   <extensions />
   <ambientOcclusionMultiplier value="255" />
   <artificialAmbientOcclusion value="255" />
   <tintValue value="0" />
  </Item>
  <Item type="CEntityDef">
   <archetypeName>hash_CF5F1839</archetypeName>
   <flags value="1572864" />
   <guid value="0" />
   <position x="2757.422" y="1967.346" z="78.84443" />
   <rotation x="0" y="0" z="-0.6360783" w="0.7716246" />
   <scaleXY value="1" />
   <scaleZ value="1" />
   <parentIndex value="-1" />
   <lodDist value="120" />
   <childLodDist value="0" />
   <lodLevel>LODTYPES_DEPTH_ORPHANHD</lodLevel>
   <numChildren value="0" />
   <priorityLevel>PRI_REQUIRED</priorityLevel>
   <extensions />
   <ambientOcclusionMultiplier value="255" />
   <artificialAmbientOcclusion value="255" />
   <tintValue value="0" />
  </Item>
  <Item type="CEntityDef">
   <archetypeName>hash_C90EB9A6</archetypeName>
   <flags value="2147483680" />
   <guid value="0" />
   <position x="2760.631" y="1965.916" z="77.68097" />
   <rotation x="0" y="0" z="0.7716245" w="0.6360783" />
   <scaleXY value="1" />
   <scaleZ value="1" />
   <parentIndex value="-1" />
   <lodDist value="50" />
   <childLodDist value="0" />
   <lodLevel>LODTYPES_DEPTH_ORPHANHD</lodLevel>
   <numChildren value="0" />
   <priorityLevel>PRI_REQUIRED</priorityLevel>
   <extensions />
   <ambientOcclusionMultiplier value="255" />
   <artificialAmbientOcclusion value="255" />
   <tintValue value="0" />
  </Item>
  <Item type="CEntityDef">
   <archetypeName>hash_214F7D27</archetypeName>
   <flags value="2147483680" />
   <guid value="0" />
   <position x="2761.17" y="1964.518" z="77.69119" />
   <rotation x="0" y="0" z="0.7716245" w="0.6360783" />
   <scaleXY value="1" />
   <scaleZ value="1" />
   <parentIndex value="-1" />
   <lodDist value="50" />
   <childLodDist value="0" />
   <lodLevel>LODTYPES_DEPTH_ORPHANHD</lodLevel>
   <numChildren value="0" />
   <priorityLevel>PRI_REQUIRED</priorityLevel>
   <extensions />
   <ambientOcclusionMultiplier value="255" />
   <artificialAmbientOcclusion value="255" />
   <tintValue value="0" />
  </Item>
  <Item type="CEntityDef">
   <archetypeName>hash_214F7D27</archetypeName>
   <flags value="2147483680" />
   <guid value="0" />
   <position x="2760.621" y="1964.625" z="77.69119" />
   <rotation x="0" y="0" z="0.7716245" w="0.6360783" />
   <scaleXY value="1" />
   <scaleZ value="1" />
   <parentIndex value="-1" />
   <lodDist value="50" />
   <childLodDist value="0" />
   <lodLevel>LODTYPES_DEPTH_ORPHANHD</lodLevel>
   <numChildren value="0" />
   <priorityLevel>PRI_REQUIRED</priorityLevel>
   <extensions />
   <ambientOcclusionMultiplier value="255" />
   <artificialAmbientOcclusion value="255" />
   <tintValue value="0" />
  </Item>
  <Item type="CEntityDef">
   <archetypeName>hash_214F7D27</archetypeName>
   <flags value="2147483680" />
   <guid value="0" />
   <position x="2760.843" y="1964.582" z="78.11256" />
   <rotation x="0" y="0" z="0.7716245" w="0.6360783" />
   <scaleXY value="1" />
   <scaleZ value="1" />
   <parentIndex value="-1" />
   <lodDist value="50" />
   <childLodDist value="0" />
   <lodLevel>LODTYPES_DEPTH_ORPHANHD</lodLevel>
   <numChildren value="0" />
   <priorityLevel>PRI_REQUIRED</priorityLevel>
   <extensions />
   <ambientOcclusionMultiplier value="255" />
   <artificialAmbientOcclusion value="255" />
   <tintValue value="0" />
  </Item>
  <Item type="CEntityDef">
   <archetypeName>hash_8C377FDB</archetypeName>
   <flags value="2147483680" />
   <guid value="0" />
   <position x="2760.584" y="1963.008" z="77.67452" />
   <rotation x="0" y="0" z="0.7716245" w="0.6360783" />
   <scaleXY value="1" />
   <scaleZ value="1" />
   <parentIndex value="-1" />
   <lodDist value="50" />
   <childLodDist value="0" />
   <lodLevel>LODTYPES_DEPTH_ORPHANHD</lodLevel>
   <numChildren value="0" />
   <priorityLevel>PRI_REQUIRED</priorityLevel>
   <extensions />
   <ambientOcclusionMultiplier value="255" />
   <artificialAmbientOcclusion value="255" />
   <tintValue value="0" />
  </Item>
  <Item type="CEntityDef">
   <archetypeName>hash_E0C0CEAD</archetypeName>
   <flags value="2147483680" />
   <guid value="0" />
   <position x="2757.278" y="1964.331" z="77.67452" />
   <rotation x="0" y="0" z="0.7716245" w="0.6360783" />
   <scaleXY value="1" />
   <scaleZ value="1" />
   <parentIndex value="-1" />
   <lodDist value="50" />
   <childLodDist value="0" />
   <lodLevel>LODTYPES_DEPTH_ORPHANHD</lodLevel>
   <numChildren value="0" />
   <priorityLevel>PRI_REQUIRED</priorityLevel>
   <extensions />
   <ambientOcclusionMultiplier value="255" />
   <artificialAmbientOcclusion value="255" />
   <tintValue value="0" />
  </Item>
  <Item type="CEntityDef">
   <archetypeName>hash_E0C0CEAD</archetypeName>
   <flags value="2147483680" />
   <guid value="0" />
   <position x="2757.894" y="1964.211" z="77.67452" />
   <rotation x="0" y="0" z="0.7716245" w="0.6360783" />
   <scaleXY value="1" />
   <scaleZ value="1" />
   <parentIndex value="-1" />
   <lodDist value="50" />
   <childLodDist value="0" />
   <lodLevel>LODTYPES_DEPTH_ORPHANHD</lodLevel>
   <numChildren value="0" />
   <priorityLevel>PRI_REQUIRED</priorityLevel>
   <extensions />
   <ambientOcclusionMultiplier value="255" />
   <artificialAmbientOcclusion value="255" />
   <tintValue value="0" />
  </Item>
  <Item type="CEntityDef">
   <archetypeName>hash_E0C0CEAD</archetypeName>
   <flags value="2147483680" />
   <guid value="0" />
   <position x="2757.561" y="1964.276" z="78.56717" />
   <rotation x="0" y="0" z="0.09584546" w="0.9953963" />
   <scaleXY value="1" />
   <scaleZ value="1" />
   <parentIndex value="-1" />
   <lodDist value="50" />
   <childLodDist value="0" />
   <lodLevel>LODTYPES_DEPTH_ORPHANHD</lodLevel>
   <numChildren value="0" />
   <priorityLevel>PRI_REQUIRED</priorityLevel>
   <extensions />
   <ambientOcclusionMultiplier value="255" />
   <artificialAmbientOcclusion value="255" />
   <tintValue value="0" />
  </Item>
  <Item type="CEntityDef">
   <archetypeName>hash_202056B3</archetypeName>
   <flags value="2147483680" />
   <guid value="0" />
   <position x="2760.117" y="1960.632" z="77.67452" />
   <rotation x="0" y="0" z="-0.6360783" w="0.7716246" />
   <scaleXY value="1" />
   <scaleZ value="1" />
   <parentIndex value="-1" />
   <lodDist value="50" />
   <childLodDist value="0" />
   <lodLevel>LODTYPES_DEPTH_ORPHANHD</lodLevel>
   <numChildren value="0" />
   <priorityLevel>PRI_REQUIRED</priorityLevel>
   <extensions />
   <ambientOcclusionMultiplier value="255" />
   <artificialAmbientOcclusion value="255" />
   <tintValue value="0" />
  </Item>
  <Item type="CEntityDef">
   <archetypeName>hash_202056B3</archetypeName>
   <flags value="2147483680" />
   <guid value="0" />
   <position x="2757.136" y="1962.446" z="77.67452" />
   <rotation x="0" y="0" z="0.7716245" w="0.6360783" />
   <scaleXY value="1" />
   <scaleZ value="1" />
   <parentIndex value="-1" />
   <lodDist value="50" />
   <childLodDist value="0" />
   <lodLevel>LODTYPES_DEPTH_ORPHANHD</lodLevel>
   <numChildren value="0" />
   <priorityLevel>PRI_REQUIRED</priorityLevel>
   <extensions />
   <ambientOcclusionMultiplier value="255" />
   <artificialAmbientOcclusion value="255" />
   <tintValue value="0" />
  </Item>
  <Item type="CEntityDef">
   <archetypeName>hash_26E644F4</archetypeName>
   <flags value="2147483680" />
   <guid value="0" />
   <position x="2757.223" y="1962.897" z="77.68533" />
   <rotation x="0" y="0" z="0.7716245" w="0.6360783" />
   <scaleXY value="1" />
   <scaleZ value="1" />
   <parentIndex value="-1" />
   <lodDist value="50" />
   <childLodDist value="0" />
   <lodLevel>LODTYPES_DEPTH_ORPHANHD</lodLevel>
   <numChildren value="0" />
   <priorityLevel>PRI_REQUIRED</priorityLevel>
   <extensions />
   <ambientOcclusionMultiplier value="255" />
   <artificialAmbientOcclusion value="255" />
   <tintValue value="0" />
  </Item>
  <Item type="CEntityDef">
   <archetypeName>hash_186436E0</archetypeName>
   <flags value="2147483680" />
   <guid value="0" />
   <position x="2756.874" y="1960.59" z="77.68663" />
   <rotation x="0" y="0" z="0.4924237" w="-0.8703557" />
   <scaleXY value="1" />
   <scaleZ value="1" />
   <parentIndex value="-1" />
   <lodDist value="50" />
   <childLodDist value="0" />
   <lodLevel>LODTYPES_DEPTH_ORPHANHD</lodLevel>
   <numChildren value="0" />
   <priorityLevel>PRI_REQUIRED</priorityLevel>
   <extensions />
   <ambientOcclusionMultiplier value="255" />
   <artificialAmbientOcclusion value="255" />
   <tintValue value="0" />
  </Item>
  <Item type="CEntityDef">
   <archetypeName>hash_8FD0E6B3</archetypeName>
   <flags value="2147483680" />
   <guid value="0" />
   <position x="2758.533" y="1961.958" z="79.88776" />
   <rotation x="0" y="0" z="0.7716245" w="0.6360783" />
   <scaleXY value="1" />
   <scaleZ value="1" />
   <parentIndex value="-1" />
   <lodDist value="50" />
   <childLodDist value="0" />
   <lodLevel>LODTYPES_DEPTH_ORPHANHD</lodLevel>
   <numChildren value="0" />
   <priorityLevel>PRI_REQUIRED</priorityLevel>
   <extensions />
   <ambientOcclusionMultiplier value="255" />
   <artificialAmbientOcclusion value="255" />
   <tintValue value="0" />
  </Item>
  <Item type="CEntityDef">
   <archetypeName>hash_8FD0E6B3</archetypeName>
   <flags value="2147483680" />
   <guid value="0" />
   <position x="2759.293" y="1965.871" z="79.88776" />
   <rotation x="0" y="0" z="0.7716245" w="0.6360783" />
   <scaleXY value="1" />
   <scaleZ value="1" />
   <parentIndex value="-1" />
   <lodDist value="50" />
   <childLodDist value="0" />
   <lodLevel>LODTYPES_DEPTH_ORPHANHD</lodLevel>
   <numChildren value="0" />
   <priorityLevel>PRI_REQUIRED</priorityLevel>
   <extensions />
   <ambientOcclusionMultiplier value="255" />
   <artificialAmbientOcclusion value="255" />
   <tintValue value="0" />
  </Item>
  <Item type="CEntityDef">
   <archetypeName>hash_8FD0E6B3</archetypeName>
   <flags value="2147483680" />
   <guid value="0" />
   <position x="2758.533" y="1961.958" z="89.35587" />
   <rotation x="0" y="0" z="0.7716245" w="0.6360783" />
   <scaleXY value="1" />
   <scaleZ value="1" />
   <parentIndex value="-1" />
   <lodDist value="50" />
   <childLodDist value="0" />
   <lodLevel>LODTYPES_DEPTH_ORPHANHD</lodLevel>
   <numChildren value="0" />
   <priorityLevel>PRI_REQUIRED</priorityLevel>
   <extensions />
   <ambientOcclusionMultiplier value="255" />
   <artificialAmbientOcclusion value="255" />
   <tintValue value="0" />
  </Item>
  <Item type="CEntityDef">
   <archetypeName>hash_8FD0E6B3</archetypeName>
   <flags value="2147483680" />
   <guid value="0" />
   <position x="2759.302" y="1965.913" z="89.35587" />
   <rotation x="0" y="0" z="0.7716245" w="0.6360783" />
   <scaleXY value="1" />
   <scaleZ value="1" />
   <parentIndex value="-1" />
   <lodDist value="50" />
   <childLodDist value="0" />
   <lodLevel>LODTYPES_DEPTH_ORPHANHD</lodLevel>
   <numChildren value="0" />
   <priorityLevel>PRI_REQUIRED</priorityLevel>
   <extensions />
   <ambientOcclusionMultiplier value="255" />
   <artificialAmbientOcclusion value="255" />
   <tintValue value="0" />
  </Item>
  <Item type="CEntityDef">
   <archetypeName>hash_35C9A934</archetypeName>
   <flags value="2147483680" />
   <guid value="0" />
   <position x="2756.269" y="1963.821" z="77.69032" />
   <rotation x="0" y="0" z="0.09584546" w="0.9953963" />
   <scaleXY value="1" />
   <scaleZ value="1" />
   <parentIndex value="-1" />
   <lodDist value="50" />
   <childLodDist value="0" />
   <lodLevel>LODTYPES_DEPTH_ORPHANHD</lodLevel>
   <numChildren value="0" />
   <priorityLevel>PRI_REQUIRED</priorityLevel>
   <extensions />
   <ambientOcclusionMultiplier value="255" />
   <artificialAmbientOcclusion value="255" />
   <tintValue value="0" />
  </Item>
  <Item type="CEntityDef">
   <archetypeName>hash_330A4ACE</archetypeName>
   <flags value="2147483680" />
   <guid value="0" />
   <position x="2754.811" y="1967.09" z="77.69032" />
   <rotation x="0" y="0" z="0.09584546" w="0.9953963" />
   <scaleXY value="1" />
   <scaleZ value="1" />
   <parentIndex value="-1" />
   <lodDist value="50" />
   <childLodDist value="0" />
   <lodLevel>LODTYPES_DEPTH_ORPHANHD</lodLevel>
   <numChildren value="0" />
   <priorityLevel>PRI_REQUIRED</priorityLevel>
   <extensions />
   <ambientOcclusionMultiplier value="255" />
   <artificialAmbientOcclusion value="255" />
   <tintValue value="0" />
  </Item>
  <Item type="CEntityDef">
   <archetypeName>hash_304AFDA1</archetypeName>
   <flags value="2147483680" />
   <guid value="0" />
   <position x="2754.319" y="1964.39" z="77.64643" />
   <rotation x="0" y="0" z="-0.6360781" w="0.7716248" />
   <scaleXY value="1" />
   <scaleZ value="1" />
   <parentIndex value="-1" />
   <lodDist value="50" />
   <childLodDist value="0" />
   <lodLevel>LODTYPES_DEPTH_ORPHANHD</lodLevel>
   <numChildren value="0" />
   <priorityLevel>PRI_REQUIRED</priorityLevel>
   <extensions />
   <ambientOcclusionMultiplier value="255" />
   <artificialAmbientOcclusion value="255" />
   <tintValue value="0" />
  </Item>
  <Item type="CEntityDef">
   <archetypeName>hash_99F1989F</archetypeName>
   <flags value="2147483680" />
   <guid value="0" />
   <position x="2754.638" y="1966.204" z="77.78939" />
   <rotation x="0" y="0" z="0.09584546" w="0.9953963" />
   <scaleXY value="1" />
   <scaleZ value="1" />
   <parentIndex value="-1" />
   <lodDist value="50" />
   <childLodDist value="0" />
   <lodLevel>LODTYPES_DEPTH_ORPHANHD</lodLevel>
   <numChildren value="0" />
   <priorityLevel>PRI_REQUIRED</priorityLevel>
   <extensions />
   <ambientOcclusionMultiplier value="255" />
   <artificialAmbientOcclusion value="255" />
   <tintValue value="0" />
  </Item>
 </entities>
 <containerLods itemType="rage__fwContainerLodDef" />
 <boxOccluders itemType="BoxOccluder" />
 <occludeModels itemType="OccludeModel" />
 <physicsDictionaries />
 <instancedData>
  <ImapLink />
  <PropInstanceList itemType="rage__fwPropInstanceListDef" />
  <GrassInstanceList itemType="rage__fwGrassInstanceListDef" />
 </instancedData>
 <timeCycleModifiers itemType="CTimeCycleModifier" />
 <carGenerators itemType="CCarGen" />
 <LODLightsSOA>
  <direction itemType="FloatXYZ" />
  <falloff />
  <falloffExponent />
  <timeAndStateFlags />
  <hash />
  <coneInnerAngle />
  <coneOuterAngleOrCapExt />
  <coronaIntensity />
 </LODLightsSOA>
 <DistantLODLightsSOA>
  <position itemType="FloatXYZ" />
  <RGBI />
  <numStreetLights value="0" />
  <category value="0" />
 </DistantLODLightsSOA>
 <block>
  <version value="0" />
  <flags value="0" />
  <name></name>
  <exportedBy>CodeWalker</exportedBy>
  <owner></owner>
  <time>05 julho 2026 06:13</time>
 </block>
</CMapData>
